Workbook

Sheet Summary v69
A1: QueryBook Composite Feature Registry v69
A2: Rows highlighted yellow on the Feature Registry sheet were added in v66 or v69 (column K). Verified Agent Transport is supported, not included: see the Supported External Services sheet. All v65 rows (columns A–G) and all v66 rows are unchanged.
A4: Measure | B4: Value
A5: Total features | B5: =COUNTA('Feature Registry v69'!A2:A383) -> 382
A6: Features carried from v65 | B6: =COUNTIF('Feature Registry v69'!K2:K383,"v65 or earlier") -> 293
A7: Features added in v66 | B7: =COUNTIF('Feature Registry v69'!K2:K383,"v66") -> 70
A8: Features added in v69 (support for agent-wrapper services, FIG. 56) | B8: =COUNTIF('Feature Registry v69'!K2:K383,"v69") -> 19
A9: External services supported (not QueryBook features) | B9: =COUNT('Supported External Services'!F2:F20) -> 2
A10: Features with a drawing reference | B10: =COUNTIF('Feature Registry v69'!H2:H383,"?*") -> 192
A11: Features with a worked expression | B11: =SUMPRODUCT(--('Feature Registry v69'!G2:G383<>"")) -> 270
A12: New features built in prototype v9.64 | B12: =COUNTIF('Feature Registry v69'!I2:I383,"Built — prototype v9.64") -> 53
A13: New features built in laboratory prototype | B13: =COUNTIF('Feature Registry v69'!I2:I383,"Built — laboratory prototype") -> 8
A14: New features specified (not yet built) | B14: =COUNTIF('Feature Registry v69'!I2:I383,"Specified") -> 28
A15: Algorithms documented | B15: =COUNTA('Algorithms (v69)'!A2:A20) -> 19
A16: Drawings (FIG. 1–56) | B16: =COUNTA('Drawings FIG 1-56'!A2:A57) -> 56
A17: Drawings referenced by at least one feature | B17: =COUNTIF('Drawings FIG 1-56'!D2:D57,">0") -> 48
A19: Features by domain | B19: All | C19: New in v66 | D19: New in v69
A20: Access, Rights & Retention | B20: =COUNTIF('Feature Registry v69'!C2:C383,A20) -> 25 | C20: =COUNTIFS('Feature Registry v69'!C2:C383,A20,'Feature Registry v69'!K2:K383,"v66") -> 6 | D20: =COUNTIFS('Feature Registry v69'!C2:C383,A20,'Feature Registry v69'!K2:K383,"v69") -> 3
A21: Authoring, Editions & Publication | B21: =COUNTIF('Feature Registry v69'!C2:C383,A21) -> 20 | C21: =COUNTIFS('Feature Registry v69'!C2:C383,A21,'Feature Registry v69'!K2:K383,"v66") -> 5 | D21: =COUNTIFS('Feature Registry v69'!C2:C383,A21,'Feature Registry v69'!K2:K383,"v69") -> 0
A22: Commerce & Entitlement Tokens | B22: =COUNTIF('Feature Registry v69'!C2:C383,A22) -> 17 | C22: =COUNTIFS('Feature Registry v69'!C2:C383,A22,'Feature Registry v69'!K2:K383,"v66") -> 1 | D22: =COUNTIFS('Feature Registry v69'!C2:C383,A22,'Feature Registry v69'!K2:K383,"v69") -> 1
A23: External Integration & Analysis | B23: =COUNTIF('Feature Registry v69'!C2:C383,A23) -> 32 | C23: =COUNTIFS('Feature Registry v69'!C2:C383,A23,'Feature Registry v69'!K2:K383,"v66") -> 11 | D23: =COUNTIFS('Feature Registry v69'!C2:C383,A23,'Feature Registry v69'!K2:K383,"v69") -> 6
A24: Grounded Expression | B24: =COUNTIF('Feature Registry v69'!C2:C383,A24) -> 21 | C24: =COUNTIFS('Feature Registry v69'!C2:C383,A24,'Feature Registry v69'!K2:K383,"v66") -> 4 | D24: =COUNTIFS('Feature Registry v69'!C2:C383,A24,'Feature Registry v69'!K2:K383,"v69") -> 0
A25: Inference, Prediction & Calibration | B25: =COUNTIF('Feature Registry v69'!C2:C383,A25) -> 35 | C25: =COUNTIFS('Feature Registry v69'!C2:C383,A25,'Feature Registry v69'!K2:K383,"v66") -> 0 | D25: =COUNTIFS('Feature Registry v69'!C2:C383,A25,'Feature Registry v69'!K2:K383,"v69") -> 1
A26: Ingestion & Sensory Intake | B26: =COUNTIF('Feature Registry v69'!C2:C383,A26) -> 35 | C26: =COUNTIFS('Feature Registry v69'!C2:C383,A26,'Feature Registry v69'!K2:K383,"v66") -> 11 | D26: =COUNTIFS('Feature Registry v69'!C2:C383,A26,'Feature Registry v69'!K2:K383,"v69") -> 1
A27: Interaction Surfaces | B27: =COUNTIF('Feature Registry v69'!C2:C383,A27) -> 26 | C27: =COUNTIFS('Feature Registry v69'!C2:C383,A27,'Feature Registry v69'!K2:K383,"v66") -> 1 | D27: =COUNTIFS('Feature Registry v69'!C2:C383,A27,'Feature Registry v69'!K2:K383,"v69") -> 0
A28: Knowledge Substrate | B28: =COUNTIF('Feature Registry v69'!C2:C383,A28) -> 19 | C28: =COUNTIFS('Feature Registry v69'!C2:C383,A28,'Feature Registry v69'!K2:K383,"v66") -> 2 | D28: =COUNTIFS('Feature Registry v69'!C2:C383,A28,'Feature Registry v69'!K2:K383,"v69") -> 2
A29: Learning & Assessment | B29: =COUNTIF('Feature Registry v69'!C2:C383,A29) -> 5 | C29: =COUNTIFS('Feature Registry v69'!C2:C383,A29,'Feature Registry v69'!K2:K383,"v66") -> 0 | D29: =COUNTIFS('Feature Registry v69'!C2:C383,A29,'Feature Registry v69'!K2:K383,"v69") -> 0
A30: Ontology & Conceptual Structure | B30: =COUNTIF('Feature Registry v69'!C2:C383,A30) -> 11 | C30: =COUNTIFS('Feature Registry v69'!C2:C383,A30,'Feature Registry v69'!K2:K383,"v66") -> 0 | D30: =COUNTIFS('Feature Registry v69'!C2:C383,A30,'Feature Registry v69'!K2:K383,"v69") -> 0
A31: Platform Governance & Evolution | B31: =COUNTIF('Feature Registry v69'!C2:C383,A31) -> 51 | C31: =COUNTIFS('Feature Registry v69'!C2:C383,A31,'Feature Registry v69'!K2:K383,"v66") -> 21 | D31: =COUNTIFS('Feature Registry v69'!C2:C383,A31,'Feature Registry v69'!K2:K383,"v69") -> 3
A32: Prime Directive | B32: =COUNTIF('Feature Registry v69'!C2:C383,A32) -> 6 | C32: =COUNTIFS('Feature Registry v69'!C2:C383,A32,'Feature Registry v69'!K2:K383,"v66") -> 0 | D32: =COUNTIFS('Feature Registry v69'!C2:C383,A32,'Feature Registry v69'!K2:K383,"v69") -> 0
A33: Retrieval & Response | B33: =COUNTIF('Feature Registry v69'!C2:C383,A33) -> 40 | C33: =COUNTIFS('Feature Registry v69'!C2:C383,A33,'Feature Registry v69'!K2:K383,"v66") -> 8 | D33: =COUNTIFS('Feature Registry v69'!C2:C383,A33,'Feature Registry v69'!K2:K383,"v69") -> 2
A34: World Model & Perception | B34: =COUNTIF('Feature Registry v69'!C2:C383,A34) -> 39 | C34: =COUNTIFS('Feature Registry v69'!C2:C383,A34,'Feature Registry v69'!K2:K383,"v66") -> 0 | D34: =COUNTIFS('Feature Registry v69'!C2:C383,A34,'Feature Registry v69'!K2:K383,"v69") -> 0

Sheet Feature Registry v69
A1: No. | B1: Feature | C1: Domain | D1: Citation | E1: Function | F1: Rule | G1: Worked expression | H1: Drawing reference (FIG.) | I1: Status | J1: Prototype module | K1: Registry version added
A2: 1 | B2: Standard Q&A | C2: Retrieval & Response | D2: §52.13.2 | E2: User-facing§52.13.2Reader Parse the query, retrieve candidate Fact Units via the Associative Recall Engine, run the Attractor Network to stabilize the candidate set, compose a response through the Narrative Graph's grounded-generation pipeline, deliver. | F2: Retrieval confidence must clear a minimum threshold before a Fact Unit is offered as grounding. | G2: =IF(0.62>=0.5,"Included as Grounding","Excluded") -> Included as Grounding | H2: 18, 48 | K2: v65 or earlier
A3: 2 | B3: Guided Exploration | C3: Retrieval & Response | D3: §52.13.2 | E3: User-facing§52.13.2Reader As Standard Q&A, but each turn's candidate retrieval is conditioned on the accumulated Cognitive Context Window from prior turns rather than the query alone. | F3: Context weight decays with turn distance; a fact from 5 turns ago counts less than one from the last turn. | G3: =1/(1+2) -> 0.33333333 | H3: 48 | K3: v65 or earlier
A4: 3 | B4: Discussion Mode | C4: Retrieval & Response | D4: §52.13.3 | E4: User-facing§52.13.3Reader / Researcher Retrieve Fact Units as in Standard Q&A; adopt a text-grounded viewpoint only where the source material's groundedness for that viewpoint clears a threshold. | F4: Viewpoint adoption is gated on a groundedness score exceeding a fixed threshold. | G4: =IF(0.8>0.6,"Adopt Viewpoint","Retrieve Only") -> Adopt Viewpoint | H4: 48 | K4: v65 or earlier
A5: 4 | B5: Tutorial Mode | C5: Retrieval & Response | D5: §52.13.2 | E5: User-facing§52.13.2Student Sequence a book's Fact Units into ordered instructional steps of increasing difficulty. | F5: Steps are ordered by a difficulty rank; a step's position is its rank among all steps. | G5: =RANK(3,{1,2,3,4,5}) -> 3 | K5: v65 or earlier
A6: 5 | B6: Comprehension Check | C6: Learning & Assessment | D6: §52.13.2 | E6: User-facing§52.13.2Student Generate a question from a target Fact Unit; compare a submitted answer's semantic similarity against that Fact Unit's content; correct if similarity clears a threshold. | F6: Answer correctness is a threshold comparison on a semantic-similarity score. | G6: =IF(0.87>=0.75,"Correct","Incorrect") -> Correct | K6: v65 or earlier
A7: 6 | B7: Semantic Exploration | C7: Retrieval & Response | D7: §52.13.2 | E7: User-facing§52.13.2Reader / Researcher Traverse the Ontology Mesh outward from a starting node, surfacing connected nodes ranked by relationship strength. | F7: Neighbors are included only above a relationship-strength threshold. | G7: =IF(0.55>=0.4,"Include Neighbor","Exclude") -> Include Neighbor | H7: 4 | K7: v65 or earlier
A8: 7 | B8: Timeline Reconstruction | C8: Retrieval & Response | D8: §52.13.2 | E8: User-facing§52.13.2Reader Extract TemporalAnchor fields from a book's Fact Units and order them chronologically. | F8: Chronological ordering is a pairwise date comparison. | G8: =IF(DATE(1848,3,14)<DATE(1849,1,1),"Event A First","Event B First") -> Event A First | K8: v65 or earlier
A9: 8 | B9: Edition Comparison | C9: Retrieval & Response | D9: §52.13.2 | E9: User-facing§52.13.2Reader Diff the VersionChain entries of two edition-tagged Fact Unit sets, surfacing additions, removals, and changes. | F9: A field differs between editions if its two values are unequal. | G9: =IF("v2 text"<>"v1 text","Changed","Same") -> Changed | K9: v65 or earlier
A10: 9 | B10: Flashcard Generation | C10: Retrieval & Response | D10: §52.13.2.1 | E10: User-facing§52.13.2.1Student Select a Fact Unit, derive a question/answer pair from its content and SupportingFactUnits, format as a citing study card. | F10: Structural rule: One flashcard derives from exactly one Fact Unit; a card spanning two Fact Units is not generated. | K10: v65 or earlier
A11: 10 | B11: Fact Graph Visualization | C11: Interaction Surfaces | D11: §52.13.2.2 | E11: User-facing§52.13.2.2Researcher Render Ontology Mesh nodes and edges for a given scope as an explicit graph structure. | F11: Structural rule: The rendered graph contains exactly the nodes and edges within the requester's scope description; no node is drawn that traversal would not return. | H11: 4 | K11: v65 or earlier
A12: 11 | B12: Inline Fact Previews | C12: Interaction Surfaces | D12: §52.13.2.2 | E12: User-facing§52.13.2.2Reader On hover/tap of a cited fact reference, retrieve and display that Fact Unit's summary without a new query round-trip. | F12: Structural rule: A preview resolves the cited Fact Unit already retrieved for the response; it issues no new query and can surface no record the response did not cite. | K12: v65 or earlier
A13: 12 | B13: Contextual Footnotes | C13: Interaction Surfaces | D13: §52.13.2.1 | E13: User-facing§52.13.2.1Reader Attach a Fact Unit's supplementary detail as an inline, dismissible footnote at its citation point. | F13: Structural rule: A footnote attaches at the citation point of the Fact Unit it elaborates and is dismissible without altering the response body. | K13: v65 or earlier
A14: 13 | B14: Personal Notes | C14: Interaction Surfaces | D14: Chapter 63 | E14: User-facingChapter 63Reader Store reader-authored text as a Fact Unit with AccessControlList restricted to the authoring reader alone. | F14: Access is granted only when the requester's identity matches the note's owner. | G14: =IF("reader_42"="reader_42","Access Granted","Denied") -> Access Granted | K14: v65 or earlier
A15: 14 | B15: Social Annotations | C15: Interaction Surfaces | D15: §52.13.2.1 | E15: User-facing§52.13.2.1 / Ch63Reader As Personal Notes, but AccessControlList defaults to author-configured sharing rather than reader-private. | F15: Visibility depends on a sharing flag rather than strict owner-match. | G15: =IF(TRUE(),"Visible to Others","Private") -> Visible to Others | K15: v65 or earlier
A16: 15 | B16: Message Boards | C16: Interaction Surfaces | D16: Chapter 64 | E16: User-facingChapter 64Reader / Author Route a post into one of four board-type partitions per the poster's role; apply moderation-action checks on write. | F16: Board partition is selected from a fixed enumeration by type index. | G16: =CHOOSE(2,"Book-Wide","Chapter","Class","Announcement") -> Chapter | K16: v65 or earlier
A17: 16 | B17: Private Messaging | C17: Access, Rights & Retention | D17: §82.2 | E17: User-facing§82.2Reader / Author Write a DirectMessage Fact Unit with AccessControlList restricted to exactly the sending and receiving identity. | F17: Access is granted only to the two identities named on the message. | G17: =IF(OR("reader_9"="reader_9","reader_9"="author_3"),"Access Granted","Denied") -> Access Granted | K17: v65 or earlier
A18: 17 | B18: Reader History Interface | C18: Access, Rights & Retention | D18: §36.8 | E18: User-facing§36.8Reader Chronological record of every session across every owned book, each entry expandable to show what was retrieved. | F18: Sessions are ordered by timestamp, most recent first. | G18: =IF(DATE(2026,8,10)>DATE(2026,8,1),"Shown First","Shown Later") -> Shown First | K18: v65 or earlier
A19: 18 | B19: Cross-Book Thematic Analysis | C19: Access, Rights & Retention | D19: Chapter 36 | E19: User-facingChapter 36Reader / Student Analyze a reader's own query-history Fact Units for recurring semantic clusters, then match against Ontology Mesh nodes in other owned books. | F19: A cross-book match requires cluster similarity above a threshold. | G19: =IF(0.71>=0.6,"Genuine Connection","No Match") -> Genuine Connection | H19: 4 | K19: v65 or earlier
A20: 19 | B20: QBQL Structured Query | C20: Retrieval & Response | D20: Chapter 18 | E20: User-facingChapter 18Researcher Parse a declarative query against the Fact Graph schema, resolve predicates, execute as a deterministic read-only traversal. | F20: Pure function of (query, current state) — no side effects. | H20: 6 | K20: v65 or earlier
A21: 20 | B21: NLPL Natural-Language Programs | C21: Retrieval & Response | D21: Chapter 48 | E21: User-facingChapter 48Researcher / Author Break the natural-language instruction into its constituent components before any code is generated. | F21: Structural rule: Decomposition into operational intents completes before any intent is bound to a concrete entity; an ambiguous binding halts compilation rather than resolving it. | K21: v65 or earlier
A22: 21 | B22: Application Library and Generator | C22: Authoring, Editions & Publication | D22: Chapter 39 | E22: User-facingChapter 39Reader Match a plain-language request against the existing template library by task/domain similarity; compose a new template only where no adequate match exists. | F22: A library match is used only above a similarity threshold; below it, composition is triggered. | G22: =IF(0.4>=0.65,"Use Existing Template","Compose New Template") -> Compose New Template | K22: v65 or earlier
A23: 22 | B23: Video Colorization & Upscaling (VCUM) | C23: Authoring, Editions & Publication | D23: Chapter 44 | E23: User-facingChapter 44Reader / Researcher Semantic Colorization Engine infers plausible color per-region from identified material class and lighting; upscaling synthesizes detail constrained to remain consistent with the source. | F23: Deterministic inference function: identical inputs always yield the identical inferred color. | H23: 16 | K23: v65 or earlier
A24: 23 | B24: Immersive 3D Scenes (IQR) | C24: Interaction Surfaces | D24: Chapter 46 | E24: User-facingChapter 46Reader Where grounding Fact Units carry sufficient spatial detail, instantiate WASM Fact Units as a renderable 3D scene. | F24: Scene rendering is triggered only once spatial-detail sufficiency clears a threshold. | G24: =IF(0.8>=0.7,"Render 3D Scene","Text Only") -> Render 3D Scene | H24: 5 | K24: v65 or earlier
A25: 24 | B25: Tour and Exhibition Mode | C25: Interaction Surfaces | D25: §46.9 | E25: User-facing§46.9Author / Reader Sequence author-selected IQR scenes into ordered Waypoints; playback steps through at reader-controlled pace. | F25: Waypoint order is a fixed sequence index. | G25: =INDEX({"Scene A","Scene B","Scene C"},2) -> Scene B | H25: 5 | K25: v65 or earlier
A26: 25 | B26: Presenter Mode | C26: Interaction Surfaces | D26: §46.10 | E26: User-facing§46.10Author Verify the requested presence mode against the author's current, mode-specific, non-revoked Author Authorization Record. | F26: Authorization is granted only if the specific mode is both authorized and not revoked. | G26: =IF(AND(TRUE(),NOT(FALSE())),"Authorized","Denied") -> Authorized | K26: v65 or earlier
A27: 26 | B27: Instructor-Created Tours | C27: Interaction Surfaces | D27: Chapter 83 | E27: User-facingChapter 83Instructor Sequence a Tour from already-published scenes, composed by an instructor rather than the author; carries non-removable ContentRole = INSTRUCTOR attribution. | F27: Attribution label is fixed by content role, not editable by the instructor. | G27: =IF("INSTRUCTOR"="INSTRUCTOR","Label: Instructor-Created","Label: Author-Curated") -> Label: Instructor-Created | H27: 5 | K27: v65 or earlier
A28: 27 | B28: Instructor Notes | C28: Interaction Surfaces | D28: §83.1 | E28: User-facing§83.1Instructor As Personal Notes, but AccessControlList is scoped to the instructor's class roster. | F28: Access is granted only to identities on the class roster. | G28: =IF(COUNTIF({"student_1","student_2","student_3"},"student_2")>0,"Access Granted","Denied") -> Access Granted | K28: v65 or earlier
A29: 28 | B29: Session Books | C29: Interaction Surfaces | D29: §84.1 | E29: User-facing§84.1Reader / Researcher Construct a delta reference over the reader's library without copying underlying Fact Units; purge on session end. | F29: The delta is a reference set, not a copy; its size is independent of the underlying library size. | K29: v65 or earlier
A30: 29 | B30: Instructor-Customized Assessment Templates | C30: Learning & Assessment | D30: §84.2 | E30: User-facing§84.2Instructor Store instructor-chosen structural parameters as a reusable template; apply structure to Comprehension Check generation while sourcing content from the Fact Graph. | F30: Question count is bounded by the template's configured maximum. | G30: =MIN(12,10) -> 10 | K30: v65 or earlier
A31: 30 | B31: Instructor Grant Visibility Dashboard | C31: Access, Rights & Retention | D31: Chapter 85 | E31: User-facingChapter 85Instructor Query all active instructor-grant Fact Units for the viewing identity; join against Class Board, Instructor Tour, and Assessment Template records. | F31: A grant is shown only while its status is active. | G31: =IF("ACTIVE"="ACTIVE","Show on Dashboard","Hide - Expired") -> Show on Dashboard | K31: v65 or earlier
A32: 31 | B32: Manuscript Upload | C32: Authoring, Editions & Publication | D32: §61.1.1 | E32: User-facing§61.1.1Author Ingest the uploaded file in a single event; tag resulting Fact Units DraftStatus = DRAFT; restrict visibility until explicit submission. | F32: Visibility is gated on DraftStatus. | G32: =IF("DRAFT"="DRAFT","Author-Only Visibility","Public") -> Author-Only Visibility | K32: v65 or earlier
A33: 32 | B33: Manuscript Editor | C33: Authoring, Editions & Publication | D33: §61.1 | E33: User-facing§61.1Author Accumulate Fact Units incrementally per edit; each edit versioned through the standard VersionChain mechanism. | F33: Each edit increments the version counter by exactly one. | G33: =3+1 -> 4 | K33: v65 or earlier
A34: 33 | B34: Narrative Coherence Checking | C34: Authoring, Editions & Publication | D34: §61.2 | E34: User-facing§61.2Author Apply Discussion Mode's critical-analysis capability to the draft's own Fact Graph, surfacing internal contradictions. | F34: A contradiction is flagged when two Fact Units assert incompatible values for the same subject/field. | G34: =IF("alive"<>"deceased","Contradiction Found","Consistent") -> Contradiction Found | H34: 7 | K34: v65 or earlier
A35: 34 | B35: Counterfactual Exploration (Drafting) | C35: Authoring, Editions & Publication | D35: §61.3 | E35: User-facing§61.3Author Construct a Scenario Graph COUNTERFACTUAL branch from the draft's current state, preserving both branches. | F35: Both counterfactual branches are preserved; branch count after divergence is two. | G35: =IF(1+1>=2,"Both branches preserved","Branch lost") -> Both branches preserved | K35: v65 or earlier
A36: 35 | B36: Supplemental Content | C36: Access, Rights & Retention | D36: §82.1 | E36: User-facing§82.1Author Ingest author-provided material, tag ContentRole = SUPPLEMENTAL, link to the parent book without altering its Rights Validation status. | F36: Rights status is read-only from the supplemental-ingestion path; it cannot be modified by this operation. | G36: =IF("VALIDATED"="VALIDATED","Rights Status Unchanged","Rights Status Unchanged") -> Rights Status Unchanged | K36: v65 or earlier
A37: 36 | B37: Multi-Author Collaboration | C37: Authoring, Editions & Publication | D37: Chapter 74 | E37: User-facingChapter 74Co-Authors Detect concurrent-write divergence via VersionChain head comparison. | F37: A conflict exists when two authors' starting version heads differ from the current head. | G37: =IF(3<>5,"Conflict Detected","No Conflict") -> Conflict Detected | K37: v65 or earlier
A38: 37 | B38: Author-Hosted Reader Events | C38: Authoring, Editions & Publication | D38: Chapter 62 | E38: User-facingChapter 62Author / Instructor Register an external collaboration platform once via the Source Connector Registry; dispatch scheduling/invitation calls through it. | F38: Structural rule: An event operation is dispatched only through a connector registered under a declared capability; the platform's broader authority does not become system authority. | K38: v65 or earlier
A39: 38 | B39: Class Boards | C39: Interaction Surfaces | D39: §64.1 | E39: User-facing§64.1Instructor / Student As Message Boards, scoped to a specific instructor + class pairing. | F39: Structural rule: Board scope is the intersection of an instructor identity and a class roster; a post is visible only within that pairing. | K39: v65 or earlier
A40: 39 | B40: Publisher Submission and Print-on-Demand | C40: Authoring, Editions & Publication | D40: Chapter 60 | E40: User-facingChapter 60Publisher / Author Accept a manuscript/title submission and route it into the publishing workflow. | F40: Structural rule: Rights validation precedes routing into the publishing workflow; an unvalidated submission does not enter it. | K40: v65 or earlier
A41: 40 | B41: Market Analytics | C41: Authoring, Editions & Publication | D41: §60.6 | E41: User-facing§60.6Publisher Aggregate distribution and usage Fact Units for a title into standard reporting views. | F41: A total is the sum of per-region unit counts. | G41: =SUM(120,340,75) -> 535 | K41: v65 or earlier
A42: 41 | B42: Moderation Appeals | C42: Platform Governance & Evolution | D42: Chapter 75 | E42: User-facingChapter 75Reader / Author Affected identity submits an AppealUnit referencing the original moderation action's Provenance Ledger entry. | F42: Structural rule: An appeal is evaluated by a reviewer other than the moderator whose action is appealed, and references that action's ledger entry. | H42: 4 | K42: v65 or earlier
A43: 42 | B43: Data Export / Portability | C43: Access, Rights & Retention | D43: Chapter 72 | E43: User-facingChapter 72Reader / Author / Researcher Query all Fact Units the requesting identity has rights to within scope; serialize to the target open format with provenance attached; continued access is unaffected. | F43: Structural rule: Export covers exactly the Fact Units the requesting identity holds rights to; export is not conditioned on continuing entitlement and withdraws no access. | K43: v65 or earlier
A44: 43 | B44: Accessibility Suite | C44: Authoring, Editions & Publication | D44: Chapter 71 | E44: User-facingChapter 71Reader Generate the required accessible-equivalent Fact Unit from the same source at production time; gate production-complete status on the equivalent's presence. | F44: Content is production-complete only if its accessible equivalent also exists. | G44: =IF(AND(TRUE(),TRUE()),"Production Complete","Incomplete - Missing Equivalent") -> Production Complete | K44: v65 or earlier
A45: 44 | B45: Precision Geometric/Color Registration | C45: World Model & Perception | D45: §46.10.8 | E45: User-facing§46.10.8 / Ch70Author Represent presenter reference material as Color Fact Units with a DeltaEThreshold; run the 3-pass Registration Constraint Graph solver; surface any drift finding rather than auto-correcting. | F45: ΔE (CIE76) computed per Waypoint transition; a finding is raised when ΔE exceeds the authored threshold. | G45: =SQRT((50-52)^2+(20-19)^2+((-10)-(-11))^2) -> 2.4494897 | K45: v65 or earlier
A46: 45 | B46: Geometric Proof Engine | C46: World Model & Perception | D46: §70.9 | E46: User-facing§70.9Researcher / Student Apply a fixed rule set to existing Geometry/Constraint Fact Units, producing a cited proof step for each derived relationship; halt on contradiction. | F46: Illustrates the complementary-angle rule with example angles 35°/55°. | G46: =IF(35+55=90,"Complementary","Not Complementary") -> Complementary | K46: v65 or earlier
A47: 46 | B47: Human Reasoning and Motivation Modeling | C47: Inference, Prediction & Calibration | D47: Chapter 80 | E47: User-facingChapter 80Researcher Construct Goal/Motivation Fact Units with a mandatory Subject reference; represent pursuit via Scenario Graph PLANNING anchored to WASM Affordance data. | F47: Confidence in an inferred (vs. stated) motivation is discounted relative to a directly-stated one. | G47: =0.9*0.6 -> 0.54 | K47: v65 or earlier
A48: 47 | B48: Autonomous Agent Connector | C48: External Integration & Analysis | D48: §49.3.3.6 | E48: User-facing§49.3.3.6Author / Publisher Dispatch a QBPL-compiled, declared action to a registered external agent per its Capability Declaration; log request/result to the Provenance Ledger. | F48: An action is only dispatched if it appears in the connector's declared capability set. | G48: =IF(COUNTIF({"schedule_event","send_invite"},"schedule_event")>0,"Dispatch Allowed","Blocked - Undeclared") -> Dispatch Allowed | H48: 14 | K48: v65 or earlier
A49: 48 | B49: Optional External Fact-Retrieval Connector | C49: External Integration & Analysis | D49: Chapter 81 | E49: User-facingChapter 81Researcher Dispatch a directed query to a registered external fact-retrieval connector, where one is registered, and convert the returned result into a native Fact Unit at the connector boundary under the ordinary ingestion path, safety evaluation and confidence calibration. The connector is one connector among others under the capability-declaration contract; it is optional, it is not a substrate, and every mechanism of this specification operates identically where none is registered. A separately-patented external system of this kind may be connected on these terms without becoming a component or a dependency. | F49: Core operation is invariant to connector presence: the mechanism set executed is identical whether or not an external fact-retrieval connector is registered. | G49: =IF(COUNTIF({"registered","absent"},"absent")>0,"Core operates identically","Core operates identically") -> Core operates identically | K49: v65 or earlier
A50: 49 | B50: Human-Directed Improvement Proposals | C50: Platform Governance & Evolution | D50: §78.6 | E50: User-facing§78.6Entitled Author / Admin Accept a directly-submitted Proposal Fact Unit from an entitled identity, bypassing telemetry-based identification but not the downstream sandbox/pre-screen/review stages. | F50: Structural rule: A human-submitted proposal enters the same evaluation and approval gate as a telemetry-identified one; bypassing telemetry does not bypass review. | K50: v65 or earlier
A51: 50 | B51: Fact Unit Schema | C51: Knowledge Substrate | D51: Chapter 3 / Appendix A | E51: Every knowledge unit is instantiated with a fixed field set regardless of source modality or FactType. | F51: FUID is a deterministic function of (content, source, timestamp). | K51: v65 or earlier
A52: 51 | B52: Multimodal Ingestion Pipeline | C52: Ingestion & Sensory Intake | D52: Chapter 4 | E52: Identify which of the eight defined modalities the incoming content matches. | F52: Detection selects the modality with the highest match score among the eight defined bits. | G52: =INDEX({"Text","Structured","Image","Audio","Video","Sensor","KG","Code"},MATCH(MAX({0.1,0.9,0.2,0.05,0.1,0,0,0}),{0.1,0.9,0.2,0.05,0.1,0,0,0},0)) -> Structured | K52: v65 or earlier
A53: 52 | B53: Classification Fallback | C53: Ingestion & Sensory Intake | D53: §4.2.1 | E53: Attempt best-effort resolution to the nearest of the eight modalities; halt with a stated reason where no reasonable resolution exists. | F53: Resolution proceeds only if best-match confidence clears a minimum threshold; otherwise halt. | G53: =IF(0.3>=0.5,"Resolve to Nearest Modality","Halt - Unclassified") -> Halt - Unclassified | K53: v65 or earlier
A54: 53 | B54: Provenance Ledger | C54: Knowledge Substrate | D54: Chapter 5 | E54: Append each consequential operation as a node in a Merkle DAG; compute a keyed checksum sufficient to detect a Safety Substrate bypass. | F54: A checksum mismatch indicates the recorded safety evaluation does not match what actually ran. | G54: =IF("A1B2C3"="A1B2C3","Checksum Valid","Bypass Detected") -> Checksum Valid | H54: 1, 4 | K54: v65 or earlier
A55: 54 | B55: Ontology Mesh | C55: Ontology & Conceptual Structure | D55: Chapter 6 | E55: Build relationship edges between Fact Units only where the underlying facts actually connect, not from statistical co-occurrence. | F55: An edge is created only if a real, named relationship type applies. | G55: =IF(COUNTIF({"causal","comparative","shared-entity"},"causal")>0,"Edge Created","No Edge") -> Edge Created | H55: 4 | K55: v65 or earlier
A56: 55 | B56: Neuromorphic Cognitive Layer / Attractor Network | C56: Retrieval & Response | D56: Chapter 7 | E56: Given an initial candidate activation set, iteratively update each activation using neighboring weighted activations until convergence. | F56: a_i(t+1) = sign( Σ_j W_ij × a_j(t) − θ_i ), reliable capacity ≈ 0.14N stable patterns for N units. | G56: =SIGN(SUMPRODUCT({0.5,0.3,-0.2},{1,1,0})-0.1) -> 1 | H56: 18 | K56: v65 or earlier
A57: 56 | B57: Safety Substrate | C57: Prime Directive | D57: Chapter 8 | E57: Evaluate every operation against SafetyFlags-derived rules at each mandatory, synchronous enforcement point. | F57: An operation proceeds only if it passes every one of its applicable gates. | G57: =IF(AND(TRUE(),TRUE(),TRUE()),"Proceed","Blocked at Gate") -> Proceed | H57: 1 | K57: v65 or earlier
A58: 57 | B58: Semantic Transport Layer | C58: Retrieval & Response | D58: Chapter 9 | E58: Route Fact Units between subsystems based on FactType and subscriber-declared filter predicates. | F58: A subscriber receives a Fact Unit only if it matches every declared filter predicate. | G58: =IF(AND(TRUE(),TRUE()),"Delivered to Subscriber","Filtered Out") -> Delivered to Subscriber | H58: 17 | K58: v65 or earlier
A59: 58 | B59: Predictive Inference Engine (PIE) | C59: Inference, Prediction & Calibration | D59: Chapter 10 | E59: Integrate four input streams into a probabilistic forward projection of future knowledge states, with confidence intervals. | F59: Illustrates the trend-projection component only — output is an interval estimate, not a single deterministic value. | G59: =TREND({10,12,14,16},{1,2,3,4},5) -> 18 | H59: 19 | K59: v65 or earlier
A60: 59 | B60: Scenario Graph | C60: Inference, Prediction & Calibration | D60: Chapter 11 | E60: Represent a hypothetical as a Knowledge State Snapshot delta rather than copying the full graph; prune low-probability branches against a threshold. | F60: A branch is pruned when its probability falls below the configured threshold. | G60: =IF(0.03<0.05,"Prune Branch","Retain Branch") -> Prune Branch | K60: v65 or earlier
A61: 60 | B61: Narrative Graph | C61: Grounded Expression | D61: Chapter 12 | E61: Construct typed edges between Fact Units to mediate response composition; flag narrative gaps where no supporting edge exists. | F61: Structural rule: Every Narrative Graph edge references at least one Fact Unit; an edge without such a reference is not constructed. | K61: v65 or earlier
A62: 61 | B62: QueryBook Format (QBF) | C62: Knowledge Substrate | D62: Chapter 13 | E62: Serialize Fact Units to a binary frame format permitting resynchronization to the next valid frame after corrupted data. | F62: Structural rule: A frame boundary is recoverable without reparsing the preceding frame, so a corrupt frame costs one frame rather than the stream. | K62: v65 or earlier
A63: 62 | B63: Storage Architecture | C63: Knowledge Substrate | D63: Chapter 14 | E63: Tier Fact Units across storage layers by access-recency/frequency; index for similarity and exact-match retrieval. | F63: A Fact Unit is promoted to a hotter tier once its access count exceeds a threshold. | G63: =IF(42>20,"Promote to Hot Tier","Remain in Current Tier") -> Promote to Hot Tier | K63: v65 or earlier
A64: 63 | B64: AGI Extension Modules (AEM) | C64: Inference, Prediction & Calibration | D64: Chapter 15 | E64: Synthesize a new derived insight from multiple existing Fact Units where no single Fact Unit directly answers a query. | F64: A synthesized insight carries a confidence trajectory distinct from, and generally lower than, any single contributing fact. | G64: =MIN(0.8,0.75) -> 0.75 | K64: v65 or earlier
A65: 64 | B65: Multilingual Regeneration Engine (MRE) | C65: Grounded Expression | D65: Chapter 16 | E65: Regenerate output in a target language directly from the language-independent Narrative Graph and SemanticHash-linked Fact Units. | F65: Back-translation of a regenerated output must yield a SemanticHash within the configured distance of the original (§16.5). | G65: =IF(0.04<=0.05,"Round-trip within tolerance","Regeneration rejected") -> Round-trip within tolerance | H65: 15 | K65: v65 or earlier
A66: 65 | B66: Cross-Domain Rule Engine (CDRE) | C66: Ontology & Conceptual Structure | D66: Chapter 17 | E66: Evaluate a probabilistically-weighted, temporally-scoped rule set incrementally, maintaining a persistent Conflict Index. | F66: A contradiction entry is added to the index when two active rules produce incompatible conclusions. | G66: =IF("true"<>"false","Contradiction Logged","Consistent") -> Contradiction Logged | K66: v65 or earlier
A67: 66 | B67: QBQL (execution floor) | C67: Retrieval & Response | D67: Chapter 18 | E67: Execute a declarative query as a read-only graph traversal with no mutation or control-flow capability. | F67: Pure function of (query, state) — no hidden state carried between evaluations. | H67: 6 | K67: v65 or earlier
A68: 67 | B68: QBPL (bounded program layer) | C68: Retrieval & Response | D68: §48.3, §48.5 | E68: Compile to one of nine fixed primitives; REPEAT-UNTIL-BOUND enforces a hard iteration ceiling at compile time. | F68: Primitive set is finite (|P| = 9); non-Turing-complete by construction. | G68: =MIN(150,100) -> 100 | K68: v65 or earlier
A69: 68 | B69: Clarification Generation Engine | C69: Retrieval & Response | D69: Chapter 37 | E69: Detect genuine referential ambiguity or a repetition/frustration signal; generate an anchored clarifying question rather than guessing. | F69: Ambiguity is flagged when top-candidate confidence scores are too close to separate. | G69: =IF(ABS(0.51-0.49)<0.1,"Ask Clarifying Question","Proceed") -> Ask Clarifying Question | K69: v65 or earlier
A70: 69 | B70: Natural Language Interaction Layer (NLIL) | C70: Retrieval & Response | D70: Chapter 50 | E70: Select vocabulary, structural format, and explanatory depth for phrasing based on inferred audience profile; the underlying fact is never altered. | F70: The selected audience profile must resolve to a defined expertise level; the underlying Fact Unit is never altered by the selection. | G70: =IF(AND(4>=1,4<=7),"Audience profile applied; fact unaltered","Refused - expertise level out of range") -> Audience profile applied; fact unaltered | H70: 13, 48 | K70: v65 or earlier
A71: 70 | B71: Fact Universe Architecture | C71: Retrieval & Response | D71: Chapter 51 | E71: Define the structural relationship between the Fact Graph, Ontology Mesh, and Provenance Ledger as coordinated views over one substrate. | F71: Structural rule: The Fact Graph, Ontology Mesh and Provenance Ledger are addressable as one structure over which a single scope description resolves. | H71: 4 | K71: v65 or earlier
A72: 71 | B72: Adaptive Response Engine (ARE, pipeline) | C72: Retrieval & Response | D72: §52.8 | E72: Analyze the candidate Fact Units retrieved for a specific query. | F72: Structural rule: Response profile resolution completes before generation begins; the directive is fixed for the response and is not renegotiated mid-generation. | H72: 13 | K72: v65 or earlier
A73: 72 | B73: World Aware System Model (WASM) | C73: World Model & Perception | D73: Chapter 53 | E73: Maintain Object, Relation, Physics, and Affordance layers as Fact Units, queryable by IQR for scene instantiation. | F73: Structural rule: Object, Relation, Physics and Affordance layers are maintained as Fact Units and are queryable on the same terms as any other record. | K73: v65 or earlier
A74: 73 | B74: Conceptual Memory Layer (CML) | C74: Ontology & Conceptual Structure | D74: Chapter 54 | E74: Persist long-term, stable world-model abstractions distinct from the transient Cognitive Context Window. | F74: Structural rule: An abstraction persisted to long-term store retains the generalized concept and discards the episode it derived from. | K74: v65 or earlier
A75: 74 | B75: Sensory Abstraction Pipeline (SAP) | C75: Ingestion & Sensory Intake | D75: Chapter 55 | E75: Reduce raw perceptual input to structured concept-level Fact Units suitable for WASM/CML consumption. | F75: Structural rule: Raw perceptual input is reduced to concept-level records before admission; no raw episode is admitted to the concept store. | K75: v65 or earlier
A76: 75 | B76: VCUM Semantic Colorization Engine (SCE) | C76: Authoring, Editions & Publication | D76: §44.3.1 | E76: Infer color for content lacking reliable existing color information from material class, lighting, and historical priors. | F76: Deterministic: identical inputs always yield the identical inferred color. | H76: 16 | K76: v65 or earlier
A77: 76 | B77: VCUM Agent Specifications | C77: Authoring, Editions & Publication | D77: Chapter 45 | E77: Define the per-agent task decomposition within the VCUM restoration pipeline. | F77: Structural rule: Each restoration agent performs exactly the task its specification declares; an agent performs no task outside its declared decomposition. | H77: 16 | K77: v65 or earlier
A78: 77 | B78: Live Fact Graph | C78: External Integration & Analysis | D78: §49.2 | E78: Maintain a continuously-updating layer of the Fact Graph reflecting the most recent ingested/inferred state. | F78: Structural rule: The live layer is read as an overlay on the committed layer; a provisional provenance reference is finalized on durable write and never altered thereafter. | H78: 4 | K78: v65 or earlier
A79: 78 | B79: Continuous Query Engine (CQE) | C79: External Integration & Analysis | D79: §49.5 | E79: Register a WATCH program with a trigger clause; re-evaluate on every relevant update, re-checking Prime Directive compliance at each firing. | F79: Re-evaluation happens on every firing, not once at registration — the count of checks equals the count of firings. | G79: =5*1 -> 5 | H79: 1 | K79: v65 or earlier
A80: 79 | B80: Structural Groundedness Enforcement | C80: Grounded Expression | D80: §16 / Narrative Graph | E80: Restrict candidate output vocabulary to terms derivable from Narrative Graph edges traceable to supporting Fact Units; reject untraceable propositions. | F80: A proposition is rejected unless it traces to at least one supporting Fact Unit. | G80: =IF(1>=1,"Include in Output","Reject - Ungrounded") -> Include in Output | H80: 13 | K80: v65 or earlier
A81: 80 | B81: Offline Synchronization Layer | C81: Knowledge Substrate | D81: Chapter 68 | E81: Select a sync mode based on connectivity; reconcile divergent offline/online states via version-vector comparison on reconnection. | F81: Reconciliation is required whenever the offline and online version vectors differ. | G81: =IF(4<>7,"Reconciliation Required","Already in Sync") -> Reconciliation Required | H81: 12 | K81: v65 or earlier
A82: 81 | B82: Portal / Role Model | C82: Access, Rights & Retention | D82: Chapter 65 | E82: AdminChapter 65Platform Admin Resolve an identity's accessible capabilities as the union of held Role(s) plus active capability grants, each evaluated independently. | F82: Access to a capability is the logical OR of role-based and grant-based access, never merged into a combined elevated set. | G82: =IF(OR(FALSE(),TRUE()),"Access Granted","Denied") -> Access Granted | K82: v65 or earlier
A83: 82 | B83: Improvement Proposal Pipeline | C83: Platform Governance & Evolution | D83: Chapter 66 | E83: AdminChapter 66Platform Admin Telemetry-driven or human-directed identification of a subsystem-scoped improvement candidate. | F83: Structural rule: A candidate is scoped to a single subsystem; a candidate targeting a member of the permanently-excluded set is refused at identification. | K83: v65 or earlier
A84: 83 | B84: QueryBook AI Evolution (System Agents) | C84: Platform Governance & Evolution | D84: Chapter 78 | E84: AdminChapter 78Platform Admin A System Agent's Candidate Identification is bounded to its assigned subsystem; resulting proposals enter the identical pipeline as any human-originated candidate. | F84: An agent cannot approve its own or another agent's proposal. | G84: =IF("agent_3"="reviewer_id","Self-Approval Blocked","Independent Review Required") -> Independent Review Required | K84: v65 or earlier
A85: 84 | B85: Formal Verification Layer | C85: Platform Governance & Evolution | D85: Chapter 79 | E85: AdminChapter 79Platform Admin Generate a machine-checked proof of a precisely-stated property for a QBPL/WATCH program or proposal. | F85: Property truth is decidable over the bounded QBPL primitive set. | G85: =IF(TRUE(),"Property Proven","Proof Failed - Property False") -> Property Proven | K85: v65 or earlier
A86: 85 | B86: License and Entitlement Management | C86: Access, Rights & Retention | D86: Chapter 67 | E86: AdminChapter 67Platform Admin Map an organizational license to Role-scoped seats; check seat and entitlement status before granting access. | F86: Access requires both an available seat and the specific entitlement. | G86: =IF(AND(TRUE(),TRUE()),"Access Granted","Denied - Missing Seat or Entitlement") -> Access Granted | K86: v65 or earlier
A87: 86 | B87: QBCL-CMS (Configuration Management) | C87: Platform Governance & Evolution | D87: Chapter 47 | E87: AdminChapter 47Platform Admin Parse and apply platform-level configuration changes through a defined configuration language, versioned like any other change. | F87: Structural rule: A configuration change is versioned and recorded on the same terms as any other change; an unversioned change is not applied. | K87: v65 or earlier
A88: 87 | B88: Source Connector Registry | C88: External Integration & Analysis | D88: §49.3.3 | E88: Admin§49.3.3Platform Admin / Author Register an external system against a fixed contract; evaluate every connector under the identical Trust Boundary regardless of name. | F88: Trust level is identical for every registered connector — not a function of the platform's name or popularity. | G88: =IF("Zoom"<>"Trust Level","Standard Trust Boundary","Standard Trust Boundary") -> Standard Trust Boundary | K88: v65 or earlier
A89: 88 | B89: Robot Memory Domain (RMD) | C89: World Model & Perception | D89: Chapter 56 | E89: AdminChapter 56Integration Operator Ingest robot/agent sensor data into Fact Units; deliver structured knowledge back; support WATCH-driven continuous behavior. | F89: Structural rule: Sensor data enters through the ordinary ingestion path and structured knowledge is returned; no raw sensory episode from an agent is retained. | K89: v65 or earlier
A90: 89 | B90: Template Debug Mode | C90: Platform Governance & Evolution | D90: Chapter 73 | E90: AdminChapter 73Platform Admin Pause execution at existing pipeline-stage boundaries, exposing Fact Unit bindings, Safety results, and Slice measurements at each pause. | F90: Structural rule: Instrumentation pauses at existing pipeline-stage boundaries of an actual execution; it introduces no stage and simulates none. | K90: v65 or earlier
A91: 90 | B91: Processor Slice Measurement Model | C91: Platform Governance & Evolution | D91: Chapter 69 | E91: AdminChapter 69Platform Admin Classify and log the compute cost of every operation into a defined Slice category; Safety Gate and Recovery Slices are prioritized above all others. | F91: Safety Gate priority always outranks any other Slice category when contended. | G91: =IF("SafetyGate"="SafetyGate","Highest Priority","Standard Priority") -> Highest Priority | K91: v65 or earlier
A92: 91 | B92: Validation and Benchmarking | C92: Platform Governance & Evolution | D92: Chapter 77 | E92: AdminChapter 77Platform Admin Define a reproducible benchmark for an existing design-target figure; run it and mark the figure validated or retract it. | F92: A design-target figure is validated only if the measured result falls within its stated tolerance. | G92: =IF(ABS(102-100)<=5,"Validated","Retracted - Out of Tolerance") -> Validated | K92: v65 or earlier
A93: 92 | B93: Platform Internationalization | C93: Platform Governance & Evolution | D93: Chapter 76 | E93: AdminChapter 76Platform Admin Apply locale-specific presentation without altering Safety Substrate or Prime Directive evaluation in any locale. | F93: Safety evaluation outcome is identical regardless of locale. | G93: =IF(TRUE()=TRUE(),"Same Safety Outcome Every Locale","N/A") -> Same Safety Outcome Every Locale | H93: 1 | K93: v65 or earlier
A94: 93 | B94: Moderation Actions | C94: Platform Governance & Evolution | D94: §64.4 | E94: Admin§64.4Author / Instructor / Platform Admin Apply a flag/hide/lock/archive action to target content, logging moderator identity and reason; reversible only via Appeals. | F94: An action is applied only if the flag count for the content reaches the configured threshold. | G94: =IF(4>=3,"Action Applied","Below Threshold - No Action") -> Action Applied | K94: v65 or earlier
A95: 94 | B95: Deployment Architecture | C95: Platform Governance & Evolution | D95: Chapter 19 | E95: AdminChapter 19Platform Admin Roll out an approved change in stages rather than all at once. | F95: Structural rule: Progression to each successive rollout stage is conditioned on the recorded human approval; no stage advances automatically. | H95: 12 | K95: v65 or earlier
A96: 95 | B96: Optional Blockchain Ownership-Verification Connector | C96: External Integration & Analysis | D96: §49.3.3.8 | E96: Admin§49.3.3.8Publisher On a resale/transfer request for a title with this connector registered, dispatch a verification query to the external service; QueryBook remains the requesting party only. | F96: Structural rule: A verification request is dispatched only for the specific title and only to the requesting party; no ownership record is retained by the system. | K96: v65 or earlier
A97: 96 | B97: Live Interaction Voice Signal Analysis | C97: External Integration & Analysis | D97: Chapter 87 | E97: User-facingChapter 87Reader If user has opted in for the session, extract prosodic features from live audio and feed as an optional trigger to the Clarification Generation Engine; discard on session end unless separately retained. | F97: Analysis runs only where session consent is active and the prosodic salience clears the trigger threshold. | G97: =IF(AND(TRUE(),0.71>=0.65),"Clarification trigger raised","No trigger") -> Clarification trigger raised | H97: 37 | K97: v65 or earlier
A98: 97 | B98: World-View Model (WVM) | C98: World Model & Perception | D98: §42.2.1System | E98: Maintain the native ontological, causal, and temporal structure underlying QueryBook's own reasoning, distinct from WASM's world-model domain and from any external hypergraph substrate. | F98: Structural rule: The ontological, causal and temporal structure is maintained natively; no external model is required to express it. | K98: v65 or earlier
A99: 98 | B99: Contextual Commerce Layer | C99: Commerce & Entitlement Tokens | D99: Chapter 88 | E99: User-facingChapter 88Reader After grounded answer is fully computed, resolve query's concept_id; match against registered commerce sources; render in separate labeled region. | F99: priority(Commerce Slice) < priority(Safety Gate Slice) for all t | G99: =IF(AND(A2="grounded_complete",B2="concept_resolved"),"eligible_for_commerce_match","blocked") -> blocked | K99: v65 or earlier
A100: 99 | B100: Commerce Processing Slice and Selection Weighting | C100: Commerce & Entitlement Tokens | D100: §88.8–§88.9System | E100: Meter each commerce operation as a bounded Slice; where multiple candidates match a resolved concept_id, select via a weighted combination of relevance, source priority, and bid, applied only to already-matched candidates. | F100: score = w1*relevance + w2*source_priority + w3*bid, Σw=1 | G100: =SUMPRODUCT({0.4,0.3,0.3},{0.9,0.7,0.6}) -> 0.75 | K100: v65 or earlier
...

Sheet Registry Record
A1: QueryBook Composite Feature Registry v65
A2: Assembled September 6, 2026, from Composite Registry v64 plus the Contextual Value Models specification, adopted as Bible v2.1 Pass 118 (§109.9) upon the inventor’s direction to specify where cultural norms, social values, ergonomics, and context are stored.
A3: Features: 293. Rows 1–279 canonical (Inventory v59). Row 280 Skill Inventory Layer (Pass 113). Rows 281–287 enhanced Fact Unit record field families (§3.8, Pass 115). Rows 288–291 record-fused encoding and database-neutral boundary (§3.9, Pass 116). Row 292 the Fact Unit Language (§3.10, Pass 117). Row 293 Contextual Value Models (§109.9, Pass 118) — registered configuration consumed by the interpretive layer, distinct from Fact Units and from World-View Model concepts. All additive.
A4: Worked expressions: 229 — unchanged.
A5: Claims: 354 (contiguous 1–354, 7 independent) — unchanged. Contextual Value Models is a where-stored specification and adds no claim; it enters Appendix A as feature 293.
A6: Additive covenant: no feature removed. Covenant floor now 293 features / 354 claims. The previously-removed mandatory external fact-transport format and external fact-query language remain removed.
A7: Canon of record: Bible v2.1 (Pass 118) · Provisional CONSOLIDATED v2.7 (Appendix A 293 features, claims 1–354) · Core Technology Overview v13 · Feature Inventory v59 · QueryBook Master Bible (Sept 1) · this Composite Registry v65.
A9: QueryBook Composite Feature Registry v66
A10: Assembled October 9, 2026, from Composite Registry v65 plus the features disclosed in Provisional Patent Application of October 9, 2026 and built in QueryBook prototype v9.64.
A11: Features: 363. Rows 1–293 carried from v65 unchanged (columns A–G). Rows 294–363 added in v66: Open Claw ingestion; on-chain certification; agent protection and deception; tamper-evident security record; agent interoperability (MCP / OpenClaw); framed hybrid transport; record-grounded colorization; the security architecture, honeypot saturation, worm defense, agent passport, post-quantum signatures and default-on-deny approval described in the application; and the October embodiments (pronunciation, speech QC, LIL, UIAS, PIL, Lecture Query, multilingual acquisition, dialects, scene director and reconstructor, key-safe mediation, editions, version-independent store, cited Q&A, deployment surfaces).
A12: New columns: H Drawing reference (FIG. 1–55 of the synchronized drawing set); I Status and J Prototype module (new rows); K Registry version added. Drawing references for v65 rows are assigned by subject and should be confirmed by counsel.
A13: New sheets: Algorithms (v66) — 13 documented algorithms with inputs, procedure, output and module; Drawings FIG 1-55 — each figure with the count of features and algorithms referencing it; Summary v66.
... A21: Status of all v69 rows: Specified — not yet built. Additive covenant: no feature removed relative to v66; no v65 cell in columns A–G altered; no v66 row altered. Claims: 357.

Sheet Algorithms (v69)
A1: ID | B1: Algorithm | C1: Features (registry) | D1: Drawing (FIG.) | E1: Inputs | F1: Procedure | G1: Output | H1: Deterministic | I1: Prototype module
A2: ALG-01 | B2: Content-based format detection | C2: Content-Based Format Detection | D2: 50 | E2: Artifact bytes | F2: 1. Read the leading bytes. 2. Match against format signatures (PDF, ZIP/OOXML, PNG, JPEG, RIFF, MP4, …). 3. For container formats, inspect internal structure (e.g. OOXML part names). 4. Fall back to text heuristics; otherwise 'unknown'. | G2: Format label | H2: Yes | I2: qb_openclaw
A3: ALG-02 | B3: Archive bomb guard | C3: Archive Expansion Bounds | D3: 50 | E3: Archive directory; bounds on depth, members, size, ratio | F3: 1. Read the archive directory without expanding. 2. Sum declared sizes, count members, compute ratio expanded/compressed, track nesting depth. 3. Refuse if any bound is exceeded. 4. Otherwise expand member by member, re-checking running totals. | G3: Expanded members or refusal | H3: Yes | I3: qb_openclaw
A4: ALG-03 | B4: Instruction-like content screen and trust floor | C4: Instruction-Like Content Screen; Untrusted-Record Trust Floor | D4: 50 | E4: Segment text (including hidden text) | F4: 1. Normalize text (case, invisible characters). 2. Match instruction-injection signatures. 3. If matched, flag the segment, set trust 0.2 (< answer threshold 0.5), record the flag in the security log. 4. Otherwise convert the segment normally. | G4: Admitted record with trust value; security-log flag | H4: Yes | I4: qb_openclaw,qb_seclog
A5: ALG-04 | B5: Certificate mint and verify | C5: Provenance Certificate Token; Independent Certificate Verifier | D5: 51 | E5: Sealed object; certificate contract address | F5: Mint: 1. Compute the object's content hash. 2. Refuse if the contract already holds a token for the hash. 3. Build metadata (kind, lineage) as an on-chain data URI. 4. Sign and send the mint transaction. Verify: 1. Recompute the hash of the held object. 2. Query the contract for the hash. 3. Report existence, holder, match, revoked, superseded. | G5: Token ID / verification report | H5: Yes | I5: qb_nft
A6: ALG-05 | B6: Deterministic transaction signing | C6: In-System Transaction Signer with Self-Test | D6: 51 | E6: Transaction fields; private key | F6: 1. At start-up, run Keccak-256, secp256k1 and RLP test vectors; disable on any failure. 2. Encode the transaction (RLP / typed). 3. Hash with Keccak-256. 4. Derive the nonce k by RFC 6979 (HMAC-DRBG). 5. Sign; normalize s to the low half-order. 6. Refuse a money-bearing chain unless elected. | G6: Signed raw transaction | H6: Yes (RFC 6979) | I6: qb_nft
A7: ALG-06 | B7: Agent Gateway admission | C7: Agent Gateway Authentication; Per-Agent Command Allow-List | D7: 52, 54 | E7: Caller ID, timestamp, keyed token, command | F7: 1. Recompute the keyed token for (caller, timestamp); compare in constant time. 2. Refuse if |now − timestamp| > 300 s or the token was seen before. 3. Refuse if the command is not on the caller's allow-list. 4. Run the deception check and firewall. 5. Record the decision. | G7: Allow / deny / isolate | H7: Yes | I7: qb_shield
A8: ALG-07 | B8: Deception trigger and isolation | C8: Honeycode; Honeytokens; Tripwires; Honeypot Agents; Impersonation-Safe Isolation Register | D8: 52 | E8: Command, parameters, connection properties | F8: 1. If the command is reserved, a honeytoken is used, a tripwire path or act is touched, or a honeypot agent is contacted: post a trigger. 2. Form the client key from the connection (loopback: address + hash of user agent). 3. Enter the key in the isolation register. 4. Route the client's further calls to the decoy and record them. | G8: Isolated session | H8: Yes | I8: qb_shield,qb_decoy
A9: ALG-08 | B9: Per-caller anomaly scoring | C9: Per-Caller Anomaly Detector | D9: 52 | E9: Per-caller request history | F9: 1. Maintain each caller's baseline rate, breadth and error pattern. 2. Score current behaviour (enumeration breadth, timing) against the baseline. 3. Post an isolation trigger above threshold. | G9: Anomaly score / trigger | H9: Yes | I9: qb_shield
A10: ALG-09 | B10: Hash-chained append and Merkle checkpoint | C10: Hash-Chained Security Record; Write-Once Signed Merkle Checkpoint | D10: 53 | E10: Security decision | F10: 1. Serialize the entry canonically. 2. h_i = SHA-256(h_{i−1} ‖ entry). 3. Every N entries: build a Merkle tree over the new entry hashes. 4. Sign root ‖ previous checkpoint hash with the deployment key (HMAC). 5. Create the checkpoint file exclusively, set read-only, mirror it, optionally anchor the root. | G10: Entry hash; checkpoint | H10: Yes | I10: qb_seclog
A11: ALG-10 | B11: Recompute-from-content verification and inclusion proof | C11: Recompute-from-Content Verifier with Inclusion Proofs | D11: 53 | E11: Log entries; checkpoints | F11: 1. Recompute every entry hash from content. 2. Recompute each Merkle root and compare. 3. Verify checkpoint signatures and chaining. 4. Compare mirrors and anchors. 5. For an entry, emit its sibling path (ceil(log2 n) hashes) as the inclusion proof. | G11: Assurance report; inclusion proof | H11: Yes | I11: qb_seclog
A12: ALG-11 | B12: Frame encode / resynchronizing decode | C12: Framed UFCS-FQL Message Format; Resynchronizing Frame Reader | D12: 55 | E12: Records or media payload | F12: Encode: 1. Compress by payload type. 2. Write the 32-byte header (marker, type, lane, flags, length, sequence). 3. Append metadata, payload, CRC32, optional signature. Decode: 1. Find a marker. 2. Check plausibility, CRC32 and signature. 3. On failure discard and scan to the next marker. | G12: Frames / recovered payloads | H12: Yes | I12: ufcs-transport-lab
... A20: ALG-19 | B20: Tool-call interception and result hashing | C20: MCP Pre-Call and Post-Call Hooks; Tool Result Record Hash | D20: 56, 54, 53 | E20: Tool call; tool result record | F20: 1. Pre-call hook receives the call and may observe, label or refuse. 2. Tool executes. 3. Hash the tool's own result record (SHA-256) and log it. 4. Post-call hook receives the result and the hash; the result record itself is immutable. | G20: Result with record hash; log entries | H20: Yes | I20: qb_mcp, qb_seclog (planned)

Sheet Drawings FIG 1-56
A1: FIG. | B1: Title | C1: Group | D1: Features referencing (count) | E1: Algorithms referencing (count)
A2: 1 | B2: QueryBook system architecture (Prime Directive as Domain 0) | C2: Core platform | D2: =SUMPRODUCT(--ISNUMBER(SEARCH(", "&A2&",",", "&'Feature Registry v69'!$H$2:$H$383&","))) -> 5 | E2: =SUMPRODUCT(--ISNUMBER(SEARCH(", "&A2&",",", "&'Algorithms (v69)'!$D$2:$D$20&","))) -> 0
A3: 2 | B3: Fact Unit — atom, envelope, and content-derived identity | C3: Core platform | D3: =SUMPRODUCT(--ISNUMBER(SEARCH(", "&A3&",",", "&'Feature Registry v69'!$H$2:$H$383&","))) -> 13 | E3: =SUMPRODUCT(--ISNUMBER(SEARCH(", "&A3&",",", "&'Algorithms (v69)'!$D$2:$D$20&","))) -> 0
A4: 3 | B4: Fact-certification authority hierarchy | C4: Core platform | D4: =SUMPRODUCT(--ISNUMBER(SEARCH(", "&A4&",",", "&'Feature Registry v69'!$H$2:$H$383&","))) -> 1 | E4: =SUMPRODUCT(--ISNUMBER(SEARCH(", "&A4&",",", "&'Algorithms (v69)'!$D$2:$D$20&","))) -> 0
A5: 4 | B5: UFCS substrate — three-store architecture | C5: Core platform | D5: =SUMPRODUCT(--ISNUMBER(SEARCH(", "&A5&",",", "&'Feature Registry v69'!$H$2:$H$383&","))) -> 14 | E5: =SUMPRODUCT(--ISNUMBER(SEARCH(", "&A5&",",", "&'Algorithms (v69)'!$D$2:$D$20&","))) -> 0
A6: 5 | B6: Authored tour and exhibition sequencing | C6: Core platform | D6: =SUMPRODUCT(--ISNUMBER(SEARCH(", "&A6&",",", "&'Feature Registry v69'!$H$2:$H$383&","))) -> 3 | E6: =SUMPRODUCT(--ISNUMBER(SEARCH(", "&A6&",",", "&'Algorithms (v69)'!$D$2:$D$20&","))) -> 0
A7: 6 | B7: FQL — joint structure and trust execution | C7: Core platform | D7: =SUMPRODUCT(--ISNUMBER(SEARCH(", "&A7&",",", "&'Feature Registry v69'!$H$2:$H$383&","))) -> 6 | E7: =SUMPRODUCT(--ISNUMBER(SEARCH(", "&A7&",",", "&'Algorithms (v69)'!$D$2:$D$20&","))) -> 1
A8: 7 | B8: Verifying machine-generated text against certified records | C8: Core platform | D8: =SUMPRODUCT(--ISNUMBER(SEARCH(", "&A8&",",", "&'Feature Registry v69'!$H$2:$H$383&","))) -> 6 | E8: =SUMPRODUCT(--ISNUMBER(SEARCH(", "&A8&",",", "&'Algorithms (v69)'!$D$2:$D$20&","))) -> 1
A9: 8 | B9: Federation — cross-boundary re-validation | C9: Core platform | D9: =SUMPRODUCT(--ISNUMBER(SEARCH(", "&A9&",",", "&'Feature Registry v69'!$H$2:$H$383&","))) -> 0 | E9: =SUMPRODUCT(--ISNUMBER(SEARCH(", "&A9&",",", "&'Algorithms (v69)'!$D$2:$D$20&","))) -> 0
A10: 9 | B10: Fact-level erasure by external-key destruction | C10: Core platform | D10: =SUMPRODUCT(--ISNUMBER(SEARCH(", "&A10&",",", "&'Feature Registry v69'!$H$2:$H$383&","))) -> 3 | E10: =SUMPRODUCT(--ISNUMBER(SEARCH(", "&A10&",",", "&'Algorithms (v69)'!$D$2:$D$20&","))) -> 0
A11: 10 | B11: Universal security architecture | C11: Core platform | D11: =SUMPRODUCT(--ISNUMBER(SEARCH(", "&A11&",",", "&'Feature Registry v69'!$H$2:$H$383&","))) -> 4 | E11: =SUMPRODUCT(--ISNUMBER(SEARCH(", "&A11&",",", "&'Algorithms (v69)'!$D$2:$D$20&","))) -> 0
A12: 11 | B12: Universal honeypot saturation and data firehose | C12: Core platform | D12: =SUMPRODUCT(--ISNUMBER(SEARCH(", "&A12&",",", "&'Feature Registry v69'!$H$2:$H$383&","))) -> 1 | E12: =SUMPRODUCT(--ISNUMBER(SEARCH(", "&A12&",",", "&'Algorithms (v69)'!$D$2:$D$20&","))) -> 0
A13: 12 | B13: Deployment topologies over an invariant common layer | C13: Core platform | D13: =SUMPRODUCT(--ISNUMBER(SEARCH(", "&A13&",",", "&'Feature Registry v69'!$H$2:$H$383&","))) -> 5 | E13: =SUMPRODUCT(--ISNUMBER(SEARCH(", "&A13&",",", "&'Algorithms (v69)'!$D$2:$D$20&","))) -> 0
... A57: 56 | B57: Support Interfaces for External Agent-Wrapper Services (Verified Agent Transport and Similar Relays) | C57: Support for agent-wrapper services | D57: =SUMPRODUCT(--ISNUMBER(SEARCH(", "&A57&",",", "&'Feature Registry v69'!$H$2:$H$383&","))) -> 19 | E57: =SUMPRODUCT(--ISNUMBER(SEARCH(", "&A57&",",", "&'Algorithms (v69)'!$D$2:$D$20&","))) -> 6

Sheet Supported External Services
A1: External service | B1: What it is | C1: Where it is described | D1: Status | E1: QueryBook support features used (registry No.) | F1: Count
A2: Verified Agent Transport (VAT) | B2: External agent-wrapper service: a sidecar relay beside an AI agent that verifies the agent's factual claims in transit, binds actions to declared intent, records every frame and verdict, and certifies each session. | C2: Separate provisional application and VAT Feature Registry (querybook/vat/docs) | D2: Specified — not yet built | E2: 364, 365, 366, 367, 368, 369, 370, 371, 372, 373, 374, 375, 376, 377, 378, 379, 380, 381, 382 | F2: 19
A3: Similar agent-wrapper relays (generic) | B3: Any external gateway, proxy or sidecar that checks an AI agent's statements or actions and needs certified facts, a tamper-evident record or session certificates. | C3: Not described in detail; supported through the same registered-caller interfaces | D3: — | E3: 382, 364, 365, 369, 375, 376, 377, 380, 381 | F3: 9
A5: External services are listed for reference only. They are not QueryBook features, are not counted in the Feature Registry, and are not claimed in the QueryBook application; QueryBook claims only the support interfaces (claims 355–357).
